{
  "address": "https://x.com/fixy_cookies/status/1758774470175564011",
  "dataMode": "json",
  "hotlinkProtected": false,
  "connectionTimeOut": -1,
  "otherPropertiesMap": {
    "CustomFolderName": "fixy_cookies",
    "CustomFileName": "fixy_cookies [2024-02-17 08ː44ː44 UTC] 1758774470175564011",
    "FileExtensionHandleMethod": "workoutExtension",
    "created_at": "Sat Feb 17 08:44:44 +0000 2024",
    "status_id": "1758774470175564011",
    "full_url": "https://x.com/fixy_cookies/status/1758774470175564011",
    "tweet_text": "https://t.co/Utv0eolydN",
    "owner_screen_name": "fixy_cookies",
    "owner_display_name": "Fixy Cookies ‼️ READ PINNED",
    "favorite_count": "1451",
    "quote_count": "0",
    "retweet_count": "90",
    "reply_count": "4",
    "is_retweet": "false",
    "is_quoted_tweet": "false",
    "is_reply_tweet": "false",
    "has_media": "true",
    "media_urls": "https://pbs.twimg.com/media/GGhsCGzW0AEmCfj?format=jpg&name=orig",
    "media_details": [
      {
        "type": "image",
        "url": "https://pbs.twimg.com/media/GGhsCGzW0AEmCfj?format=jpg&name=orig",
        "owner": "fixy_cookies"
      }
    ]
  }
}