{
  "address": "https://x.com/fur_Splash/status/1798149084890734834",
  "dataMode": "json",
  "hotlinkProtected": false,
  "connectionTimeOut": -1,
  "otherPropertiesMap": {
    "CustomFolderName": "fur_Splash",
    "CustomFileName": "fur_Splash [2024-06-05 00ː25ː24 UTC] 1798149084890734834",
    "FileExtensionHandleMethod": "workoutExtension",
    "created_at": "Wed Jun 05 00:25:24 +0000 2024",
    "status_id": "1798149084890734834",
    "full_url": "https://x.com/fur_Splash/status/1798149084890734834",
    "tweet_text": "다들 오늘 하루도 힘내요!! https://t.co/nyPVGLKBrH",
    "owner_screen_name": "fur_Splash",
    "owner_display_name": "첨벙이",
    "favorite_count": "102",
    "quote_count": "0",
    "retweet_count": "10",
    "reply_count": "0",
    "is_retweet": "false",
    "is_quoted_tweet": "false",
    "is_reply_tweet": "false",
    "has_media": "true",
    "media_urls": "https://pbs.twimg.com/media/GPRPEGna8AAcs0E?format=jpg&name=orig",
    "media_details": [
      {
        "type": "image",
        "url": "https://pbs.twimg.com/media/GPRPEGna8AAcs0E?format=jpg&name=orig",
        "owner": "fur_Splash"
      }
    ]
  }
}