{
  "address": "https://x.com/CHM_DP/status/1743889502781984861",
  "dataMode": "json",
  "hotlinkProtected": false,
  "connectionTimeOut": -1,
  "otherPropertiesMap": {
    "CustomFolderName": "CHM_DP",
    "CustomFileName": "CHM_DP [2024-01-07 06ː57ː12 UTC] 1743889502781984861",
    "FileExtensionHandleMethod": "workoutExtension",
    "created_at": "Sun Jan 07 06:57:12 +0000 2024",
    "status_id": "1743889502781984861",
    "full_url": "https://x.com/CHM_DP/status/1743889502781984861",
    "tweet_text": "https://t.co/X383gBh372",
    "owner_screen_name": "CHM_DP",
    "owner_display_name": "Hanmu",
    "favorite_count": "1278",
    "quote_count": "0",
    "retweet_count": "135",
    "reply_count": "2",
    "is_retweet": "false",
    "is_quoted_tweet": "false",
    "is_reply_tweet": "false",
    "has_media": "true",
    "media_urls": "https://pbs.twimg.com/media/GDOKQAkbEAAuNZb?format=jpg&name=orig",
    "media_details": [
      {
        "type": "image",
        "url": "https://pbs.twimg.com/media/GDOKQAkbEAAuNZb?format=jpg&name=orig",
        "owner": "CHM_DP"
      }
    ]
  }
}