{
  "address": "https://x.com/roah_83/status/1740969633296056766",
  "dataMode": "json",
  "hotlinkProtected": false,
  "connectionTimeOut": -1,
  "otherPropertiesMap": {
    "CustomFolderName": "roah_83",
    "CustomFileName": "roah_83 [2023-12-30 05ː34ː40 UTC] 1740969633296056766",
    "FileExtensionHandleMethod": "workoutExtension",
    "created_at": "Sat Dec 30 05:34:40 +0000 2023",
    "status_id": "1740969633296056766",
    "full_url": "https://x.com/roah_83/status/1740969633296056766",
    "tweet_text": "https://t.co/gmjlvXWyd0",
    "owner_screen_name": "roah_83",
    "owner_display_name": "✦Roah",
    "favorite_count": "757",
    "quote_count": "0",
    "retweet_count": "77",
    "reply_count": "0",
    "is_retweet": "false",
    "is_quoted_tweet": "false",
    "is_reply_tweet": "false",
    "has_media": "true",
    "media_urls": "https://pbs.twimg.com/media/GCkqmrFbIAADQPQ?format=jpg&name=orig",
    "media_details": [
      {
        "type": "image",
        "url": "https://pbs.twimg.com/media/GCkqmrFbIAADQPQ?format=jpg&name=orig",
        "owner": "roah_83"
      }
    ]
  }
}