{
  "address": "https://x.com/zilluzion/status/1692197090267468198",
  "dataMode": "json",
  "hotlinkProtected": false,
  "connectionTimeOut": -1,
  "otherPropertiesMap": {
    "CustomFolderName": "zilluzion",
    "CustomFileName": "zilluzion [2023-08-17 15ː30ː00 UTC] 1692197090267468198",
    "FileExtensionHandleMethod": "workoutExtension",
    "created_at": "Thu Aug 17 15:30:00 +0000 2023",
    "status_id": "1692197090267468198",
    "full_url": "https://x.com/zilluzion/status/1692197090267468198",
    "tweet_text": "💚a VERY squishy noodle, for @AipiTheAvali https://t.co/8mPUsPzJE3",
    "owner_screen_name": "zilluzion",
    "owner_display_name": "zillu ☕🧡",
    "favorite_count": "46",
    "quote_count": "0",
    "retweet_count": "6",
    "reply_count": "0",
    "is_retweet": "false",
    "is_quoted_tweet": "false",
    "is_reply_tweet": "false",
    "has_media": "true",
    "media_urls": "https://pbs.twimg.com/media/F3kOAkDWsAEBIw7?format=png&name=orig",
    "media_details": [
      {
        "type": "image",
        "url": "https://pbs.twimg.com/media/F3kOAkDWsAEBIw7?format=png&name=orig",
        "owner": "zilluzion"
      }
    ]
  }
}