{
  "address": "https://x.com/fourleafisland/status/1783188333838975170",
  "dataMode": "json",
  "hotlinkProtected": false,
  "connectionTimeOut": -1,
  "otherPropertiesMap": {
    "CustomFolderName": "fourleafisland",
    "CustomFileName": "fourleafisland [2024-04-24 17ː36ː43 UTC] 1783188333838975170",
    "FileExtensionHandleMethod": "workoutExtension",
    "created_at": "Wed Apr 24 17:36:43 +0000 2024",
    "status_id": "1783188333838975170",
    "full_url": "https://x.com/fourleafisland/status/1783188333838975170",
    "tweet_text": "some old art of eevee and its older siblings ^_^ https://t.co/bOGl1HbqHy",
    "owner_screen_name": "fourleafisland",
    "owner_display_name": "fourleafisland.art... see you in space cowboy 🏖️",
    "favorite_count": "4938",
    "quote_count": "0",
    "retweet_count": "839",
    "reply_count": "18",
    "is_retweet": "false",
    "is_quoted_tweet": "false",
    "is_reply_tweet": "false",
    "has_media": "true",
    "media_urls": "https://pbs.twimg.com/media/GL8oTHrWwAAni8C?format=jpg&name=orig",
    "media_details": [
      {
        "type": "image",
        "url": "https://pbs.twimg.com/media/GL8oTHrWwAAni8C?format=jpg&name=orig",
        "owner": "fourleafisland"
      }
    ]
  }
}